jimu/a.pyd
jimu/b.pyd
jimu/c.pyd
jimu-0.0.2.dist-info/METADATA
jimu-0.0.2.dist-info/WHEEL
jimu-0.0.2.dist-info/top_level.txt
jimu-0.0.2.dist-info/RECORD
