Metadata-Version: 2.1
Name: jimu
Version: 0.0.2
Summary: D helper
Home-page: 
Author: jimu
Author-email: jimu@gmail.com
License: Apache 2.0
Platform: Windows Only
Classifier: Programming Language :: Python :: 3
Classifier: Operating System :: Microsoft :: Windows
Requires-Dist: tdrpa.tdworker
